omuplugins/__init__.py
omuplugins-0.1.5.dist-info/METADATA
omuplugins-0.1.5.dist-info/WHEEL
omuplugins-0.1.5.dist-info/RECORD
