Metadata-Version: 2.1
Name: omuplugins
Version: 0.1.5
Summary: Add your description here
Author-email: am230 <111672334+am230@users.noreply.github.com>
Requires-Python: >=3.12
Requires-Dist: edgetrans>=0.2.3
Requires-Dist: loguru>=0.7.2
Requires-Dist: pydub>=0.25.1
